{
 "accept_payment": 1,
 "allow_comments": 0,
 "allow_delete": 0,
 "allow_edit": 0,
 "allow_incomplete": 0,
 "allow_multiple": 1,
 "allow_print": 1,
 "amount": 0.0,
 "amount_based_on_field": 1,
 "amount_field": "amount",
 "client_script": "",
 "creation": "2017-07-06 16:25:22.393979",
 "currency": "INR",
 "doc_type": "Conference Participant",
 "docstatus": 0,
 "doctype": "Web Form",
 "idx": 0,
 "introduction_text": "",
 "is_standard": 1,
 "login_required": 0,
 "max_attachment_size": 0,
 "modified": "2019-08-02 19:37:55.220738",
 "modified_by": "Administrator",
 "module": "ERPNext Foundation",
 "name": "buy-tickets-inr",
 "owner": "Administrator",
 "payment_button_label": "Buy Now",
 "payment_gateway": "Razorpay",
 "published": 1,
 "route": "buy-tickets-inr",
 "route_to_success_link": 0,
 "show_attachments": 0,
 "show_in_grid": 0,
 "show_sidebar": 0,
 "sidebar_items": [],
 "success_url": "/conf/2017",
 "title": "Buy Tickets INR",
 "web_form_fields": [
  {
   "allow_read_on_all_link_options": 0,
   "fieldname": "participant_name",
   "fieldtype": "Data",
   "hidden": 0,
   "label": "Participant Name",
   "max_length": 0,
   "max_value": 0,
   "read_only": 0,
   "reqd": 1,
   "show_in_filter": 0
  },
  {
   "allow_read_on_all_link_options": 0,
   "fieldname": "participant_designation",
   "fieldtype": "Select",
   "hidden": 0,
   "label": "Your role at your organization",
   "max_length": 0,
   "max_value": 0,
   "options": "\nCxO\nAnalyst\nConsultant\nDeveloper\nSystem Administrator\nOther",
   "read_only": 0,
   "reqd": 0,
   "show_in_filter": 0
  },
  {
   "allow_read_on_all_link_options": 0,
   "default": "",
   "fieldname": "email",
   "fieldtype": "Data",
   "hidden": 0,
   "label": "Email",
   "max_length": 0,
   "max_value": 0,
   "options": "Email",
   "read_only": 0,
   "reqd": 0,
   "show_in_filter": 0
  },
  {
   "allow_read_on_all_link_options": 0,
   "description": "Rs 4000 per person. Includes lunch and dinner on both days",
   "fieldname": "full_conference_tickets",
   "fieldtype": "Int",
   "hidden": 0,
   "label": "No of Tickets",
   "max_length": 0,
   "max_value": 0,
   "read_only": 0,
   "reqd": 0,
   "show_in_filter": 0
  },
  {
   "allow_read_on_all_link_options": 0,
   "fieldname": "tshirt_table",
   "fieldtype": "Table",
   "hidden": 0,
   "label": "T-Shirt Sizes",
   "max_length": 0,
   "max_value": 0,
   "options": "TShirt Sizes",
   "read_only": 0,
   "reqd": 0,
   "show_in_filter": 0
  },
  {
   "allow_read_on_all_link_options": 0,
   "fieldname": "tshirt_size",
   "fieldtype": "Select",
   "hidden": 0,
   "label": "T-Shirt Size",
   "max_length": 0,
   "max_value": 0,
   "options": "S\nM\nL\nXL\nXXL\nXXXL",
   "read_only": 0,
   "reqd": 0,
   "show_in_filter": 0
  },
  {
   "allow_read_on_all_link_options": 0,
   "default": "INR",
   "fieldname": "currency",
   "fieldtype": "Select",
   "hidden": 0,
   "label": "Currency",
   "max_length": 0,
   "max_value": 0,
   "options": "INR",
   "read_only": 1,
   "reqd": 1,
   "show_in_filter": 0
  },
  {
   "allow_read_on_all_link_options": 0,
   "fieldname": "amount",
   "fieldtype": "Data",
   "hidden": 0,
   "label": "Amount",
   "max_length": 0,
   "max_value": 0,
   "read_only": 1,
   "reqd": 1,
   "show_in_filter": 0
  }
 ]
}